tiletool/__init__.py
tiletool/tiletool.py
tiletool/examples/example1_generator/example1_generator.py
tiletool/examples/example1_generator/platform.png
tiletool/examples/example1_generator/platform2.png
tiletool/examples/example2_txt_and_csv/example2_txt_csv.py
tiletool/examples/example2_txt_and_csv/platform.png
tiletool/examples/example2_txt_and_csv/platform2.png
tiletool/examples/example2_txt_and_csv/temp.txt
tiletool/examples/example2_txt_and_csv/test.csv
tiletool/examples/example3_tmx/desert.tsx
tiletool/examples/example3_tmx/desert1.tmx
tiletool/examples/example3_tmx/example3_tmx.py
tiletool/examples/example3_tmx/temp.txt
tiletool/examples/example3_tmx/tmw_desert_spacing.png
tiletool/examples/example4_camera/desert.tmx
tiletool/examples/example4_camera/desert.tsx
tiletool/examples/example4_camera/example4_camera.py
tiletool/examples/example4_camera/platform.png
tiletool/examples/example4_camera/platform2.png
tiletool/examples/example4_camera/temp.txt
tiletool/examples/example4_camera/tmw_desert_spacing.png
tiletool-1.2.0.dist-info/LICENSE.txt
tiletool-1.2.0.dist-info/METADATA
tiletool-1.2.0.dist-info/WHEEL
tiletool-1.2.0.dist-info/top_level.txt
tiletool-1.2.0.dist-info/RECORD
